{"name":"CALL LIST","slug":"call-list","stats":{"total":3,"pipeline":0,"client":0,"warm":0,"cold":0,"drip":0,"untagged":3,"firmCount":3,"metroCount":1,"metros":["CALL LIST"]},"metros":["CALL LIST"],"metroBreakdown":{"CALL LIST":{"contactCount":29610,"officeCount":3,"trip":"CALL LIST"}},"offices":[{"key":"AMERIPRISE FINANCIAL|COLUMBUS","firm":"Ameriprise Financial Services, LLC","city":"Columbus","state":"OH","addr":"1070 Polaris Pkwy","industryAUM":0,"aoAUM":0,"gap":0,"penetration":0,"aoProducts":{},"peerGroups":{},"displacementScore":0,"contactCount":92,"bestContactStatus":"pipeline","contacts":[{"fn":"Suzanne","ln":"Singleton","status":"untagged","email":"Suzanne.Stacy Mckelvey@ampf.com"},{"fn":"Adam","ln":"Wetzel","status":"untagged","email":"adam.s.wetzel@ampf.com"},{"fn":"Alex","ln":"Mager","status":"untagged","email":"alex.mager@ampf.com"},{"fn":"Alexander","ln":"Reed","status":"untagged","email":"alexander.j.reed@ampf.com"},{"fn":"Andrea","ln":"Larason","status":"untagged","email":"andrea.j.larason@ampf.com"},{"fn":"Andrew","ln":"Fugazzi","status":"untagged","email":"andrew.e.fugazzi@ampf.com"},{"fn":"Andrew","ln":"Brate","status":"untagged","email":"andrew.m.brate@ampf.com"},{"fn":"Austin","ln":"Gossett","status":"untagged","email":"austin.gossett@ampf.com"},{"fn":"Susanne","ln":"Osborne","status":"untagged","email":"Susanne.Nelson@ampf.com"},{"fn":"Brad","ln":"Johnson","status":"untagged","email":"brad.2.johnson@ampf.com"},{"fn":"Branden","ln":"Kurgan","status":"untagged","email":"branden.c.kurgan@ampf.com"},{"fn":"Brandt","ln":"Cookston","status":"untagged","email":"brandt.cookston@ampf.com"},{"fn":"Susan","ln":"Golden","status":"untagged","email":"Susan.Yentz@ampf.com"},{"fn":"Brittany","ln":"Wagner","status":"untagged","email":"brittany.wagner@ampf.com"},{"fn":"Christian","ln":"Carey","status":"cold","email":"christian.carey@ampf.com"},{"fn":"Christian","ln":"Fontanez-Virella","status":"untagged","email":"Christian.Fontanez-Virella@ampf.com"},{"fn":"Christopher","ln":"Gallaugher","status":"untagged","email":"christopher.d.gallaugher@ampf.com"},{"fn":"Christopher","ln":"Tyra","status":"untagged","email":"christopher.tyra@ampf.com"},{"fn":"Christopher","ln":"Fisher","status":"untagged","email":"christopher.p.fisher@ampf.com"},{"fn":"Claire","ln":"Cookston","status":"untagged","email":"claire.cookston@ampf.com"},{"fn":"David","ln":"Rothstein","status":"untagged","email":"david.rothstein@ampf.com"},{"fn":"Dennis","ln":"Hendrix","status":"untagged","email":"dennis.hendrix@ampf.com"},{"fn":"Donnita","ln":"Mackie","status":"untagged","email":"donnita.mackie@ampf.com"},{"fn":"Ted","ln":"Inbusch","status":"untagged","email":"ted.inbusch@ampf.com"},{"fn":"Eric","ln":"Beckman","status":"untagged","email":"eric.beckman@ampf.com"},{"fn":"Eric","ln":"Koller","status":"untagged","email":"eric.j.koller@ampf.com"},{"fn":"Gabriel","ln":"Glimcher","status":"untagged","email":"gabriel.glimcher@ampf.com"},{"fn":"Helen","ln":"Colon","status":"untagged","email":"helen.colon@ampf.com"},{"fn":"Jacob","ln":"Kurgan","status":"untagged","email":"jacob.kurgan@ampf.com"},{"fn":"Jacob","ln":"Larrison","status":"untagged","email":"jacob.larrison@ampf.com"},{"fn":"Jaime","ln":"Goubeaux","status":"untagged","email":"jaime.l.goubeaux@ampf.com"},{"fn":"James","ln":"Johnson","status":"untagged","email":"james.b.johnson@ampf.com"},{"fn":"James","ln":"Gleason","status":"untagged","email":"james.m.gleason@ampf.com"},{"fn":"Summer","ln":"Hoffman","status":"untagged","email":"Summer.Diaz@ampf.com"},{"fn":"Jason","ln":"Palmer","status":"untagged","email":"jason.e.palmer@ampf.com"},{"fn":"Susan","ln":"Gilbert","status":"untagged","email":"Susan.Torbin@ampf.com"},{"fn":"Jason","ln":"Wolfe","status":"untagged","email":"jason.l.wolfe@ampf.com"},{"fn":"Jason","ln":"Helterbridle","status":"untagged","email":"jason.m.helterbridle@ampf.com"},{"fn":"Javier","ln":"Piquero","status":"untagged","email":"javier.l.piquero@ampf.com"},{"fn":"Sue","ln":"Gilbert","status":"untagged","email":"Sue.Nauss@ampf.com"},{"fn":"Jennifer","ln":"Lucus","status":"untagged","email":"jennifer.l.bryant@ampf.com"},{"fn":"Jeremy","ln":"Smythe","status":"untagged","email":"jeremy.m.smythe@ampf.com"},{"fn":"Jessica","ln":"Simpson","status":"untagged","email":"jessica.l.simpson@ampf.com"},{"fn":"Stuart","ln":"Maldonado","status":"untagged","email":"Stuart.Haw@ampf.com"},{"fn":"Joel","ln":"Railsback","status":"untagged","email":"joel.d.railsback@ampf.com"},{"fn":"John","ln":"Kurgan","status":"untagged","email":"john.x.kurgan@ampf.com"},{"fn":"Johnny","ln":"Dawson","status":"untagged","email":"johnny.dawson@ampf.com"},{"fn":"Jonathan","ln":"Hemmings","status":"untagged","email":"jon.hemmings@ampf.com"},{"fn":"Steven","ln":"Ball","status":"untagged","email":"Steven.Treberg@ampf.com"},{"fn":"Joshua","ln":"Nalli","status":"untagged","email":"jnalli@ampf.com"},{"fn":"Julia","ln":"Osborn","status":"untagged","email":"julia.osborn@ampf.com"},{"fn":"Karen","ln":"Cookston","status":"untagged","email":"karen.s.cookston@ampf.com"},{"fn":"Katherine","ln":"Taylor","status":"untagged","email":"katherine.taylor@ampf.com"},{"fn":"Kenneth","ln":"Couture","status":"untagged","email":"ken.couture@ampf.com"},{"fn":"Kerry","ln":"McMullen","status":"untagged","email":"kerry.m.mcmullen@ampf.com"},{"fn":"Kerry","ln":"Thompson","status":"untagged","email":"kerry.r.thompson@ampf.com"},{"fn":"Kevin","ln":"Clark","status":"untagged","email":"kevin.r.clark@ampf.com"},{"fn":"Kevin","ln":"Teeples","status":"untagged","email":"kevin.teeples@ampf.com"},{"fn":"Kyle","ln":"Radeloff","status":"untagged","email":"kyle.a.radeloff@ampf.com"},{"fn":"Kyle","ln":"Keber","status":"untagged","email":"kyle.keber@ampf.com"},{"fn":"Louie","ln":"Burrus","status":"untagged","email":"louie.e.burrus@ampf.com"},{"fn":"Lynn","ln":"Zag","status":"untagged","email":"lynn.2.zag@ampf.com"},{"fn":"Mark","ln":"Randall","status":"untagged","email":"mark.j.randall@ampf.com"},{"fn":"Mark","ln":"Zipfel","status":"untagged","email":"mark.zipfel@ampf.com"},{"fn":"Steven","ln":"Sangalli","status":"untagged","email":"Steven.Phillips@ampf.com"},{"fn":"Michael","ln":"Derflinger","status":"untagged","email":"michael.a.derflinger@ampf.com"},{"fn":"Michael","ln":"Rothstein","status":"untagged","email":"michael.b.rothstein@ampf.com"},{"fn":"Michael","ln":"Kuplic","status":"untagged","email":"michael.kuplic@ampf.com"},{"fn":"Michael","ln":"Kerr","status":"untagged","email":"michael.kerr@ampf.com"},{"fn":"Michael","ln":"Perez","status":"untagged","email":"michael.j.perez@ampf.com"},{"fn":"Steven","ln":"Mottice","status":"untagged","email":"Steven.Zeiger@ampf.com"},{"fn":"Mythri","ln":"Padival","status":"untagged","email":"mythri.padival@ampf.com"},{"fn":"Natalee","ln":"Adams","status":"untagged","email":"natalee.adams@ampf.com"},{"fn":"Neil","ln":"Zipfel","status":"untagged","email":"neil.zipfel@ampf.com"},{"fn":"Rachael","ln":"Holm","status":"untagged","email":"rachael.c.holm@ampf.com"},{"fn":"Raymond","ln":"Jones","status":"untagged","email":"raymond.r.jones@ampf.com"},{"fn":"Richard","ln":"Pierce","status":"untagged","email":"richard.l.pierce@ampf.com"},{"fn":"Russell","ln":"Fish","status":"untagged","email":"russell.j.fish@ampf.com"},{"fn":"Ryan","ln":"Romer-Jordan","status":"untagged","email":"ryan.m.romer-jordan@ampf.com"},{"fn":"Sara","ln":"Colton","status":"untagged","email":"sara.colton@ampf.com"},{"fn":"Sarah","ln":"Lawson","status":"untagged","email":"sarah.lawson@ampf.com"},{"fn":"Sarah","ln":"Wiersma","status":"untagged","email":"sarah.wiersma@ampf.com"},{"fn":"Scott","ln":"Bentley","status":"untagged","email":"scott.bentley@ampf.com"},{"fn":"Shawn","ln":"McCoy","status":"untagged","email":"shawn.p.mccoy@ampf.com"},{"fn":"Stephen","ln":"Daley","status":"untagged","email":"stephen.g.daley@ampf.com"},{"fn":"Stephen","ln":"Berardi","status":"untagged","email":"sberardi@ampf.com"},{"fn":"Tim","ln":"Tilton","status":"pipeline","email":"timothy.tilton@ampf.com"},{"fn":"Travis","ln":"Cremeans","status":"untagged","email":"travis.m.cremeans@ampf.com"},{"fn":"Trevor","ln":"Downing","status":"untagged","email":"trevor.downing@ampf.com"},{"fn":"William","ln":"Willson","status":"untagged","email":"william.willson@ampf.com"},{"fn":"William","ln":"Shulack","status":"untagged","email":"william.r.shulack@ampf.com"},{"fn":"Zach","ln":"Powell","status":"untagged","email":"zach.powell@ampf.com"}]},{"key":"LPL|COLUMBUS","firm":"LPL","city":"Columbus","state":"OH","addr":"7650 Rivers Edge Dr","industryAUM":0,"aoAUM":0,"gap":0,"penetration":0,"aoProducts":{},"peerGroups":{},"displacementScore":0,"contactCount":50,"bestContactStatus":"untagged","contacts":[{"fn":"Adam","ln":"Pusateri","status":"untagged","email":"adam.pusateri@lpl.com"},{"fn":"Amanda","ln":"Pennington","status":"untagged","email":"amanda.pennington@lpl.com"},{"fn":"Andy","ln":"Michel","status":"untagged","email":"andy.michel@lpl.com"},{"fn":"Andrew","ln":"Gile","status":"untagged","email":"andrew.gile@lpl.com"},{"fn":"Ann","ln":"Agozzino","status":"untagged","email":"ann.agozzino@lpl.com"},{"fn":"Austin","ln":"Fisher","status":"untagged","email":"austin.fisher@lpl.com"},{"fn":"Brett","ln":"Gladden","status":"untagged","email":"brett.gladden@lpl.com"},{"fn":"Brian","ln":"Sweeney","status":"untagged","email":"brian.sweeney@lpl.com"},{"fn":"Bryan","ln":"England","status":"untagged","email":"Bryan.England@lpl.com"},{"fn":"Cheryl Ann","ln":"Brown","status":"untagged","email":"ca.brown@lpl.com"},{"fn":"Chris","ln":"Bright","status":"untagged","email":"chris.bright@lpl.com"},{"fn":"Clayton","ln":"Irwin","status":"untagged","email":"clayton.irwin@lpl.com"},{"fn":"Clifford","ln":"Rayburn","status":"untagged","email":"Clifford.Rayburn@lpl.com"},{"fn":"Crystal","ln":"Rickard","status":"untagged","email":"crystal.rickard@lpl.com"},{"fn":"Daniel","ln":"Renz","status":"untagged","email":"daniel.renz@lpl.com"},{"fn":"Don","ln":"Parkhill","status":"untagged","email":"don.parkhill@lpl.com"},{"fn":"Greg","ln":"Bauers","status":"untagged","email":"Gregory.Bauers@lpl.com"},{"fn":"Hershel","ln":"Proffitt","status":"untagged","email":"hershel.proffitt@lpl.com"},{"fn":"James","ln":"Hunter","status":"untagged","email":"james.hunter@lpl.com"},{"fn":"James","ln":"Calvert","status":"untagged","email":"jim.calvert@lpl.com"},{"fn":"Jason","ln":"Black","status":"untagged","email":"jason.black@lpl.com"},{"fn":"Jennifer","ln":"Jenkins","status":"untagged","email":"jennifer.jenkins@lpl.com"},{"fn":"Bryan","ln":"Norris","status":"untagged","email":"bryan.norris@lpl.com"},{"fn":"John","ln":"Bean","status":"untagged","email":"john.bean@lpl.com"},{"fn":"Kyle","ln":"Mawhorr","status":"untagged","email":"kyle.mawhorr@lpl.com"},{"fn":"Jody","ln":"Davis","status":"untagged","email":"jody.davis@lpl.com"},{"fn":"Landy","ln":"Thompson","status":"untagged","email":"landy.thompson@lpl.com"},{"fn":"Mark","ln":"Snell","status":"untagged","email":"mark.snell@lpl.com"},{"fn":"Matthew","ln":"Postell","status":"untagged","email":"Matthew.Postell@lpl.com"},{"fn":"Mike","ln":"Davell","status":"untagged","email":"mike.davell@lpl.com"},{"fn":"Daniel","ln":"Zwayer","status":"untagged","email":"daniel.zwayer@lpl.com"},{"fn":"Molly","ln":"Dodane","status":"untagged","email":"molly.dodane@lpl.com"},{"fn":"Susan","ln":"Lombardo","status":"untagged","email":"susan.lombardo@lpl.com"},{"fn":"Nick","ln":"Arena","status":"untagged","email":"nicholas.arena@lpl.com"},{"fn":"Nick","ln":"Beres","status":"untagged","email":"nick.beres@lpl.com"},{"fn":"Olga","ln":"Strasser","status":"untagged","email":"Olga.Strasser@lpl.com"},{"fn":"Philip","ln":"Shively","status":"untagged","email":"philip.shively@lpl.com"},{"fn":"Richard","ln":"Obrien","status":"untagged","email":"richard.obrien@lpl.com"},{"fn":"Robert","ln":"Polletta","status":"untagged","email":"robert.polletta@lpl.com"},{"fn":"Ron","ln":"Mohr","status":"untagged","email":"ronald.mohr@lpl.com"},{"fn":"Sam","ln":"Chickerella","status":"untagged","email":"sam.chickerella@lpl.com"},{"fn":"Sean","ln":"McEvoy","status":"untagged","email":"Sean.McEvoy@lpl.com"},{"fn":"Stephen","ln":"Rogers","status":"untagged","email":"stephen.rogers@lpl.com"},{"fn":"Steven","ln":"Oxley","status":"untagged","email":"steven.oxley@lpl.com"},{"fn":"Steven","ln":"Bauers","status":"untagged","email":"Steven.Bauers@lpl.com"},{"fn":"Talia","ln":"Musolino","status":"untagged","email":"talia.musolino@lpl.com"},{"fn":"Tyler","ln":"Deck","status":"untagged","email":"tyler.deck@lpl.com"},{"fn":"Tyler","ln":"Klepek","status":"untagged","email":"tyler.klepek@lpl.com"},{"fn":"Vanessa","ln":"Bey","status":"untagged","email":"vanessa.bey@lpl.com"},{"fn":"Victor","ln":"Newman","status":"untagged","email":"victor.newman@lpl.com"}]},{"key":"HARBOUR INVESTMENTS|COLUMBUS","firm":"Harbour Investments, Inc.","city":"Columbus","state":"WI","addr":"Private Residence","industryAUM":0,"aoAUM":0,"gap":0,"penetration":0,"aoProducts":{},"peerGroups":{},"displacementScore":0,"contactCount":1,"bestContactStatus":"untagged","contacts":[{"fn":"Denise","ln":"Jaehnke","status":"untagged","email":"DJaehnke@hirep.net"}]}],"totalIndustryAUM":0,"totalAoAUM":0,"gap":0,"penetration":0,"officeCount":3,"contactCount":3,"firmCount":3}